ai_data_scrubber/__init__.py
ai_data_scrubber/scrub_text.py
ai_data_scrubber-0.1.1.dist-info/licenses/LICENSE
ai_data_scrubber-0.1.1.dist-info/METADATA
ai_data_scrubber-0.1.1.dist-info/WHEEL
ai_data_scrubber-0.1.1.dist-info/entry_points.txt
ai_data_scrubber-0.1.1.dist-info/top_level.txt
ai_data_scrubber-0.1.1.dist-info/RECORD
