Metadata-Version: 2.4
Name: ai-data-scrubber
Version: 0.1.1
Summary: A lightweight tool for removing personal data from text before uploading to LLMs
Author: Catherine Nelson
License: MIT
Project-URL: Homepage, https://github.com/catherinenelson1/ai-data-scrubber
Project-URL: Repository, https://github.com/catherinenelson1/ai-data-scrubber
Project-URL: Issues, https://github.com/catherinenelson1/ai-data-scrubber/issues
Keywords: privacy,data-cleaning,pii,llm,spacy,anonymization,text-processing
Classifier: Intended Audience :: Developers
Classifier: License :: OSI Approved :: MIT License
Classifier: Programming Language :: Python :: 3
Classifier: Programming Language :: Python :: 3.10
Classifier: Programming Language :: Python :: 3.11
Classifier: Programming Language :: Python :: 3.12
Classifier: Programming Language :: Python :: 3.13
Classifier: Topic :: Text Processing
Requires-Python: >=3.10
License-File: LICENSE
Requires-Dist: spacy>=3.5.0
Provides-Extra: dev
Requires-Dist: pytest>=8.0.0; extra == "dev"
Dynamic: license-file
